PyMovieDb/__init__.py
PyMovieDb/imdb.py
PyMovieDb/parser.py
PyMovieDb/test.py
PyMovieDb-0.0.9.dist-info/LICENSE
PyMovieDb-0.0.9.dist-info/METADATA
PyMovieDb-0.0.9.dist-info/WHEEL
PyMovieDb-0.0.9.dist-info/top_level.txt
PyMovieDb-0.0.9.dist-info/RECORD
