Metadata-Version: 2.1
Name: PyMovieDb
Version: 0.0.9
Summary: A Python Module that represents IMDB API
Home-page: https://github.com/itsmehemant7/PyMovieDb
Author: Hemant Malik
Author-email: itsmehemant7@gmail.com
License-File: LICENSE
Requires-Dist: requests-html
